gcomvkm/__init__.py
gcomvkm/cli.py
gcomvkm/demo.py
gcomvkm/g_comvkm.py
gcomvkm/data/__init__.py
gcomvkm/data/data_synthetic.mat
gcomvkm/evaluation/__init__.py
gcomvkm/evaluation/metrics.py
gcomvkm/utils/__init__.py
gcomvkm/utils/data_loader.py
gcomvkm-0.1.0.dist-info/LICENSE
gcomvkm-0.1.0.dist-info/METADATA
gcomvkm-0.1.0.dist-info/WHEEL
gcomvkm-0.1.0.dist-info/entry_points.txt
gcomvkm-0.1.0.dist-info/top_level.txt
gcomvkm-0.1.0.dist-info/RECORD
