Metadata-Version: 2.1
Name: gcomvkm
Version: 0.1.0
Summary: Globally Collaborative Multi-View k-Means Clustering Algorithm
Home-page: https://github.com/kpsinaga/gcomvkm
Author: Kristina P. Sinaga
Author-email: kristinasinaga41@gmail.com
Project-URL: Bug Tracker, https://github.com/kpsinaga/gcomvkm/issues
Classifier: Programming Language :: Python :: 3
Classifier: License :: OSI Approved :: MIT License
Classifier: Operating System :: OS Independent
Classifier: Topic :: Scientific/Engineering :: Artificial Intelligence
Classifier: Topic :: Scientific/Engineering :: Information Analysis
Requires-Python: >=3.7
License-File: LICENSE
Requires-Dist: numpy >=1.18.0
Requires-Dist: scipy >=1.4.0
Requires-Dist: matplotlib >=3.1.0
Requires-Dist: scikit-learn >=0.22.0
Requires-Dist: seaborn >=0.11.0
